LICENSE
setup.py
discumremaded/RESTapiwrap.py
discumremaded/__init__.py
discumremaded/__version__.py
discumremaded/discumremaded.py
discumremaded/importmanager.py
discumremaded/logger.py
discumremaded.egg-info/PKG-INFO
discumremaded.egg-info/SOURCES.txt
discumremaded.egg-info/dependency_links.txt
discumremaded.egg-info/requires.txt
discumremaded.egg-info/top_level.txt
discumremaded/gateway/__init__.py
discumremaded/gateway/event.py
discumremaded/gateway/gateway.py
discumremaded/gateway/parse.py
discumremaded/gateway/remoteauth.py
discumremaded/gateway/request.py
discumremaded/gateway/response.py
discumremaded/gateway/session.py
discumremaded/gateway/types.py
discumremaded/gateway/channels/__init__.py
discumremaded/gateway/channels/parse.py
discumremaded/gateway/dms/__init__.py
discumremaded/gateway/dms/request.py
discumremaded/gateway/guild/__init__.py
discumremaded/gateway/guild/combo.py
discumremaded/gateway/guild/parse.py
discumremaded/gateway/guild/request.py
discumremaded/gateway/media/__init__.py
discumremaded/gateway/media/request.py
discumremaded/gateway/messages/__init__.py
discumremaded/gateway/messages/parse.py
discumremaded/gateway/start/__init__.py
discumremaded/gateway/start/parse.py
discumremaded/gateway/user/__init__.py
discumremaded/gateway/user/combo.py
discumremaded/gateway/user/parse.py
discumremaded/gateway/user/request.py
discumremaded/guild/__init__.py
discumremaded/guild/guild.py
discumremaded/interactions/__init__.py
discumremaded/interactions/buttons.py
discumremaded/interactions/slashcommands.py
discumremaded/messages/__init__.py
discumremaded/messages/messages.py
discumremaded/science/__init__.py
discumremaded/science/science.py
discumremaded/start/__init__.py
discumremaded/start/login.py
discumremaded/start/other.py
discumremaded/start/superproperties.py
discumremaded/stickers/__init__.py
discumremaded/stickers/stickers.py
discumremaded/user/__init__.py
discumremaded/user/user.py
discumremaded/utils/__init__.py
discumremaded/utils/accessibility.py
discumremaded/utils/button.py
discumremaded/utils/client_uuid.py
discumremaded/utils/color.py
discumremaded/utils/contextproperties.py
discumremaded/utils/embed.py
